vembrane/__init__.py
vembrane/ann_types.py
vembrane/cli.py
vembrane/common.py
vembrane/errors.py
vembrane/globals.py
vembrane/representations.py
vembrane/sequence_ontology.py
vembrane/backend/backend_cyvcf2.py
vembrane/backend/backend_pysam.py
vembrane/backend/base.py
vembrane/modules/__init__.py
vembrane/modules/annotate.py
vembrane/modules/fhir.py
vembrane/modules/filter.py
vembrane/modules/sort.py
vembrane/modules/structured.py
vembrane/modules/table.py
vembrane/modules/tag.py
vembrane/modules/assets/fhir/assemblies.tsv
vembrane/modules/assets/fhir/chromosomes.tsv
vembrane/modules/assets/fhir/cytobands.tsv
vembrane/modules/assets/fhir/genomic_source_classes.tsv
vembrane/modules/assets/fhir/profiles/mii_molgen_v2025.0.0.yaml
vembrane/resources/sequence_ontology.2024-06-06.obo.xz
vembrane/resources/sequence_ontology.LICENSE
vembrane-2.4.0.dist-info/METADATA
vembrane-2.4.0.dist-info/WHEEL
vembrane-2.4.0.dist-info/entry_points.txt
vembrane-2.4.0.dist-info/licenses/LICENSE
vembrane-2.4.0.dist-info/RECORD
