Metadata-Version: 2.4
Name: vembrane
Version: 2.4.0
Summary: Filter VCF/BCF files with Python expressions.
Project-URL: homepage, https://github.com/vembrane/vembrane
Project-URL: repository, https://github.com/vembrane/vembrane
Author: Till Hartmann, Christopher Schröder, Johannes Köster, Jan Forster, Marcel Bargull, Felix Mölder, Elias Kuthe, David Lähnemann
License-File: LICENSE
Requires-Python: >=3.12
Requires-Dist: asttokens~=3.0
Requires-Dist: cyvcf2~=0.31.1
Requires-Dist: intervaltree~=3.1
Requires-Dist: networkx~=3.5
Requires-Dist: numpy~=2.1
Requires-Dist: obonet~=1.1
Requires-Dist: pysam~=0.23.3
Requires-Dist: pyyaml~=6.0
Requires-Dist: typing-extensions~=4.12
Requires-Dist: yte~=1.9
